quart_wtf/__init__.py
quart_wtf/const.py
quart_wtf/csrf.py
quart_wtf/file.py
quart_wtf/form.py
quart_wtf/i18n.py
quart_wtf/meta.py
quart_wtf/py.typed
quart_wtf/typing.py
quart_wtf/utils.py
quart_wtforms-1.0.3.dist-info/METADATA
quart_wtforms-1.0.3.dist-info/WHEEL
quart_wtforms-1.0.3.dist-info/RECORD
